aare/ClusterFinder.py
aare/ClusterVector.py
aare/CtbRawFile.py
aare/RawFile.py
aare/ScanParameters.py
aare/__init__.py
aare/_aare.cpython-311-x86_64-linux-gnu.so
aare/calibration.py
aare/func.py
aare/transform.py
aare/utils.py
aare-2025.8.22.dist-info/METADATA
aare-2025.8.22.dist-info/WHEEL
aare-2025.8.22.dist-info/RECORD
